mcp_data_analzyer_jifengsheng/__init__.py
mcp_data_analzyer_jifengsheng/__main__.py
mcp_data_analzyer_jifengsheng/cli.py
mcp_data_analzyer_jifengsheng/core.py
mcp_data_analyzer_jifengsheng-0.4.dist-info/METADATA
mcp_data_analyzer_jifengsheng-0.4.dist-info/WHEEL
mcp_data_analyzer_jifengsheng-0.4.dist-info/entry_points.txt
mcp_data_analyzer_jifengsheng-0.4.dist-info/top_level.txt
mcp_data_analyzer_jifengsheng-0.4.dist-info/RECORD
