Metadata-Version: 2.4
Name: mcp-data-analyzer-jifengsheng
Version: 0.4
Summary: a mcp-data-analzyer mcp server.
Requires-Python: >=3.10
Requires-Dist: httpx>=0.28.1
Requires-Dist: mcp[cli]>=1.13.1
Requires-Dist: openpyxl>=3.1.5
Requires-Dist: pandas>=2.3.2
Requires-Dist: seaborn>=0.13.2
Requires-Dist: twine>=6.1.0
